{
  "ridge_alpha": 1.0,
  "target": "np.log1p(trip_duration)",
  "numeric_features": [
    "passenger_count",
    "pickup_month",
    "pickup_day",
    "pickup_hour",
    "pickup_dayofweek",
    "pickup_minute",
    "is_weekend",
    "is_rush_hour",
    "is_night",
    "hour_sin",
    "hour_cos",
    "dow_sin",
    "dow_cos",
    "month_sin",
    "month_cos",
    "pickup_longitude",
    "pickup_latitude",
    "dropoff_longitude",
    "dropoff_latitude",
    "lat_diff",
    "lon_diff",
    "abs_lat_diff",
    "abs_lon_diff",
    "haversine_km",
    "manhattan_km",
    "log_haversine_km",
    "sqrt_haversine_km",
    "haversine_km_squared",
    "log_manhattan_km",
    "sqrt_manhattan_km",
    "bearing",
    "bearing_sin",
    "bearing_cos",
    "center_latitude",
    "center_longitude",
    "pickup_distance_to_center",
    "dropoff_distance_to_center",
    "pickup_jfk",
    "dropoff_jfk",
    "pickup_lga",
    "dropoff_lga",
    "pickup_ewr",
    "dropoff_ewr",
    "distance_x_rush",
    "distance_x_weekend",
    "distance_x_night",
    "distance_x_hour",
    "pickup_cell_te",
    "dropoff_cell_te",
    "route_cell_te",
    "hour_dow_te",
    "vendor_hour_te"
  ],
  "categorical_features": [
    "vendor_id",
    "store_and_fwd_flag"
  ],
  "target_encoding_columns": [
    "pickup_cell",
    "dropoff_cell",
    "route_cell",
    "hour_dow",
    "vendor_hour"
  ],
  "cleaning_thresholds": {
    "duration_low": 7.0,
    "duration_high": 85152.0,
    "distance_low": 0.0,
    "distance_high": 24.86720898630446
  },
  "train_rows_raw": 1000000,
  "train_rows_clean": 997070,
  "validation_rows_raw": 229319,
  "validation_rows_clean": 228635,
  "train_metrics": {
    "r2_log_target": 0.7160924822066832,
    "rmse_log_target": 0.4075887851018757,
    "r2_seconds": 0.11092144631036571
  },
  "validation_metrics": {
    "r2_log_target": 0.7156023104970191,
    "rmse_log_target": 0.40974262646168386,
    "r2_seconds": 0.10542267782723547
  },
  "final_model_trained_on": "train + validation",
  "final_training_rows_clean": 1225705
}